fakefarsi/__init__.py
fakefarsi/data.py
fakefarsi/fakefarsi.py
fakefarsi-0.0.8.dist-info/LICENSE
fakefarsi-0.0.8.dist-info/METADATA
fakefarsi-0.0.8.dist-info/WHEEL
fakefarsi-0.0.8.dist-info/top_level.txt
fakefarsi-0.0.8.dist-info/RECORD
