Metadata-Version: 2.1
Name: fakefarsi
Version: 0.0.8
Summary: A package for generate a fake iranian person information
Home-page: https://github.com/mhnrhmni/FakeFarsi/
Author: Mahan Rahmani
Author-email: Mahan Rahmani <mahanrahmani777@gmail.com>
Project-URL: Homepage, https://github.com/mhnrhmni/FakeFarsi
Project-URL: Issues, https://github.com/mhnrhmni/FakeFarsi/issues
Classifier: Programming Language :: Python :: 3
Classifier: License :: OSI Approved :: MIT License
Classifier: Operating System :: OS Independent 
Requires-Python: >=3.7
License-File: LICENSE
